gliaml/__init__.py
gliaml/activations.py
gliaml/network_utils.py
mlp/__init__.py
mlp/activations.py
mlp/network_utils.py
gliaml-0.1.1.dist-info/LICENSE.txt
gliaml-0.1.1.dist-info/METADATA
gliaml-0.1.1.dist-info/WHEEL
gliaml-0.1.1.dist-info/top_level.txt
gliaml-0.1.1.dist-info/RECORD
