Metadata-Version: 2.1
Name: gliaml
Version: 0.1.1
Summary: GliaML - Python Machine Learning Library
Home-page: https://github.com/Archiecool4/GliaML
Author: Archie Shahidullah
Author-email: archie@caltech.edu
License: http://www.apache.org/licenses/LICENSE-2.0
Download-URL: https://github.com/Archiecool4/GliaML
Keywords: machine learning neural networks
Platform: UNKNOWN
Classifier: Development Status :: 3 - Alpha
Classifier: Intended Audience :: Developers
Classifier: Intended Audience :: Education
Classifier: Intended Audience :: Science/Research
Classifier: License :: OSI Approved :: Apache Software License
Classifier: Programming Language :: Python :: 3.6
Classifier: Topic :: Scientific/Engineering
Classifier: Topic :: Scientific/Engineering :: Artificial Intelligence
Classifier: Topic :: Software Development
Classifier: Topic :: Software Development :: Libraries
Classifier: Topic :: Software Development :: Libraries :: Python Modules
Requires-Dist: numpy
